[{"version":"v1.0-dev","title":"v1.0-dev (87b37b1)","aliases":["v1-dev","latest-dev"]},{"version":"v1.0-pre","title":"v1.0.0-rc3","aliases":["v1-pre","latest-pre"]},{"version":"v0.25","title":"v0.25.1","aliases":["v0","latest"]},{"version":"v0.24","title":"v0.24.0","aliases":[]},{"version":"v0.23","title":"v0.23.0","aliases":[]},{"version":"v0.22","title":"v0.22.1","aliases":[]},{"version":"v0.21","title":"v0.21.1","aliases":[]},{"version":"v0.20","title":"v0.20.0","aliases":[]},{"version":"v0.19","title":"v0.19.0","aliases":[]},{"version":"v0.18","title":"v0.18.0","aliases":[]},{"version":"v0.17","title":"v0.17.0","aliases":[]},{"version":"v0.16","title":"v0.16.4","aliases":[]},{"version":"v0.15","title":"v0.15.0","aliases":[]},{"version":"v0.14","title":"v0.14.0","aliases":[]},{"version":"v0.13","title":"v0.13.0","aliases":[]},{"version":"v0.12","title":"v0.12.0","aliases":[]}]